etpy/Cash.py
etpy/Normal.py
etpy/__init__.py
etpy/app.py
etpy-0.0.12.dist-info/LICENSE
etpy-0.0.12.dist-info/METADATA
etpy-0.0.12.dist-info/WHEEL
etpy-0.0.12.dist-info/top_level.txt
etpy-0.0.12.dist-info/RECORD
