Metadata-Version: 2.1
Name: etpy
Version: 0.0.12
Summary: Reverse Engineering of My Etisalat App
Home-page: UNKNOWN
Author: TarekTurbo (Tarek Abdelraheem)
Author-email: <tarekthedream@gmail.com>
License: UNKNOWN
Keywords: python,Reverse,Enginner,My Etisalat,Internet in egypt,egpt,etisalat,masr,etisalat masr
Platform: UNKNOWN
Classifier: Development Status :: 1 - Planning
Classifier: Intended Audience :: Developers
Classifier: Programming Language :: Python :: 3
Requires-Dist: pydantic
Requires-Dist: requests
Requires-Dist: setuptools
Requires-Dist: xmltodict
